polygon_data/__init__.py
polygon_data/polygonDataFetch.py
polygon_data-0.1.2.dist-info/METADATA
polygon_data-0.1.2.dist-info/WHEEL
polygon_data-0.1.2.dist-info/top_level.txt
polygon_data-0.1.2.dist-info/RECORD
