Metadata-Version: 2.1
Name: polygon-data
Version: 0.1.2
Summary: Demo library
Home-page: https://sarthakgagdani.ml
Author: Sarthak Gagdani
Author-email: sarthak.gagdani@nyu.edu
License: MIT
Platform: UNKNOWN
Classifier: Intended Audience :: Developers
Classifier: License :: OSI Approved :: MIT License
Classifier: Programming Language :: Python
Classifier: Programming Language :: Python :: 3
Classifier: Programming Language :: Python :: 3.6
Classifier: Programming Language :: Python :: 3.7
Classifier: Programming Language :: Python :: 3.8
Classifier: Programming Language :: Python :: 3.9
Classifier: Operating System :: OS Independent
Requires-Dist: polygon-api-client
Requires-Dist: sqlalchemy
